doc.py
doc_gen-0.0.1.dist-info/entry_points.txt
doc_gen-0.0.1.dist-info/LICENSE
doc_gen-0.0.1.dist-info/WHEEL
doc_gen-0.0.1.dist-info/METADATA
doc_gen-0.0.1.dist-info/RECORD
