Metadata-Version: 2.1
Name: doc-gen
Version: 0.0.1
Summary: Set code files free from unwieldy documentation!
Author: Pradhyum R
Author-email: drpradhyum2016@outlook.com
Classifier: License :: OSI Approved :: MIT License
Requires-Dist: Pygments
Requires-Dist: prompt-toolkit
